.hgignore
CHANGES.txt
LICENSE.txt
README.txt
bootstrap.py
bootstrap.pyo
buildout.cfg
setup.py
js/__init__.py
js.json_template.egg-info/PKG-INFO
js.json_template.egg-info/SOURCES.txt
js.json_template.egg-info/dependency_links.txt
js.json_template.egg-info/entry_points.txt
js.json_template.egg-info/namespace_packages.txt
js.json_template.egg-info/not-zip-safe
js.json_template.egg-info/requires.txt
js.json_template.egg-info/top_level.txt
js/json_template/__init__.py
js/json_template/jsontemplate.py
js/json_template/test_json_template.txt
js/json_template/resources/README.txt
js/json_template/resources/json-template.js