Metadata-Version: 1.0
Name: js.json-template
Version: 0.8
Summary: Fanstatic packaging of JSON Template
Home-page: UNKNOWN
Author: Fanstatic Developers
Author-email: fanstatic@googlegroups.com
License: BSD
Platform: UNKNOWN
